{
  "db_id": "e_commerce",
  "index": 52,
  "question": "What are the ids and dates of the orders with at least two products?",
  "sql": "SELECT o.order_id, o.date_order_placed FROM Orders o JOIN Order_Items oi ON o.order_id = oi.order_id GROUP BY o.order_id HAVING COUNT(oi.order_item_id) >= 2;",
  "semantic": {
    "back_translation": {
      "intent": "查找具有至少两个商品项的订单信息",
      "tables": [
        "Orders",
        "Order_Items"
      ],
      "columns": [
        "order_id",
        "date_order_placed"
      ],
      "filters": [],
      "agg": [
        "COUNT"
      ],
      "group_by": [
        "order_id"
      ],
      "order_by": [],
      "limit": null
    },
    "score": 0.8,
    "pass": false,
    "reason": "缺少关键过滤条件，应通过COUNT(order_item_id) >= 2筛选订单，且需确保正确关联Order_Items表与Orders表"
  }
}