{
  "db_id": "tv_shows",
  "index": 139,
  "question": "What are the names and original air dates of tv shows?",
  "sql": "SELECT tv_show_name, Original_Airdate FROM tv_show;",
  "semantic": {
    "back_translation": {
      "intent": "获取电视节目名称和首播日期",
      "tables": [
        "tv_show"
      ],
      "columns": [
        "tv_show_name",
        "Original_Airdate"
      ],
      "filters": [],
      "agg": [],
      "group_by": [],
      "order_by": [],
      "limit": null
    },
    "score": 1.0,
    "pass": true,
    "reason": "语义完全一致，原始问题要求获取电视节目名称和首播日期，SQL反向翻译描述中的意图、表、列均与之匹配，且无过滤、聚合、分组或排序要求。"
  }
}