{
  "db_id": "vehicle_rent",
  "index": 420,
  "question": "What is the average age for customers with a membership credit above the average?",
  "sql": "SELECT AVG(age) FROM Customers WHERE membership_credit > (SELECT AVG(membership_credit) FROM Customers)",
  "semantic": {
    "back_translation": {
      "intent": "计算平均年龄",
      "tables": [
        "Customers"
      ],
      "columns": [
        "age"
      ],
      "filters": [
        "membership_credit > (SELECT AVG(membership_credit) FROM Customers)"
      ],
      "agg": [
        "AVG"
      ],
      "group_by": [],
      "order_by": [],
      "limit": null
    },
    "score": 1.0,
    "pass": true,
    "reason": "语义完全一致。原始问题要求计算会员信用高于整体平均值的客户群体的平均年龄，SQL反向翻译正确使用子查询获取整体平均membership_credit，并通过过滤条件筛选符合条件的客户，最终对age字段进行AVG聚合。"
  }
}