{
  "db_id": "cre_Doc_and_collections",
  "index": 680,
  "question": "How many documents owned by Marlin?",
  "sql": "SELECT COUNT(*) FROM Document_Objects WHERE Owner = 'Marlin'",
  "semantic": {
    "back_translation": {
      "intent": "统计符合条件的记录数量",
      "tables": [
        "Document_Objects"
      ],
      "columns": [],
      "filters": [
        "Owner = 'Marlin'"
      ],
      "agg": [
        "COUNT(*)"
      ],
      "group_by": [],
      "order_by": [],
      "limit": null
    },
    "score": 1.0,
    "pass": true,
    "reason": "原始问题要求统计Marlin拥有的文档数量，SQL反向翻译描述中的意图、表名、过滤条件(Owner='Marlin')和聚合函数(COUNT(*))均与之完全匹配，没有遗漏或错误的语义要素。"
  }
}