{
  "db_id": "address_1",
  "index": 835,
  "question": "What are the city name and average distances from each city?",
  "sql": "SELECT City.city_name, AVG(Direct_distance.distance) AS average_distances FROM City JOIN Direct_distance ON City.city_code = Direct_distance.city1_code OR City.city_code = Direct_distance.city2_code GROUP BY City.city_name;",
  "semantic": {
    "back_translation": {
      "intent": "计算每个城市的平均距离",
      "tables": [
        "City",
        "Direct_distance"
      ],
      "columns": [
        "City.city_name",
        "Direct_distance.distance"
      ],
      "filters": [],
      "agg": [
        "AVG(Direct_distance.distance)"
      ],
      "group_by": [
        "City.city_name"
      ],
      "order_by": [],
      "limit": null
    },
    "score": 1.0,
    "pass": true,
    "reason": "原始问题要求获取每个城市的名称及其平均距离，SQL描述通过JOIN City和Direct_distance表，使用AVG(Direct_distance.distance)聚合函数并按City.city_name分组实现该需求，且列选择和分组逻辑完全匹配。"
  }
}